neszen_helper/__init__.py
neszen_helper/utils.py
neszen_helper-0.3.0.dist-info/METADATA
neszen_helper-0.3.0.dist-info/WHEEL
neszen_helper-0.3.0.dist-info/top_level.txt
neszen_helper-0.3.0.dist-info/RECORD
