Metadata-Version: 2.1
Name: neszen_helper
Version: 0.3.0
Summary: A simple package to convert text to uppercase and lowercase
Requires-Python: >=3.6
